setup.py
kidMe/__init__.py
kidMe.egg-info/PKG-INFO
kidMe.egg-info/SOURCES.txt
kidMe.egg-info/dependency_links.txt
kidMe.egg-info/not-zip-safe
kidMe.egg-info/top_level.txt