Metadata-Version: 1.0
Name: kidMe
Version: 0.1
Summary: The funniest joke in the world
Home-page: UNKNOWN
Author: Saeed Mirshekari
Author-email: saeed.mirshekari@gmail.com
License: MIT
Platform: UNKNOWN
